andes/__init__.py
andes/__main__.py
andes/_version.py
andes/cli.py
andes/main.py
andes/plot.py
andes/shared.py
andes/system.py
andes/cases/5bus_fortescue.xlsx
andes/cases/5bus/pjm5bus.json
andes/cases/5bus/pjm5bus.xlsx
andes/cases/GBnetwork/GBnetwork.m
andes/cases/GBnetwork/GBnetwork.xlsx
andes/cases/GBnetwork/README.md
andes/cases/ei/EI_33.xlsx
andes/cases/ieee14/README.md
andes/cases/ieee14/ieee14.dyr
andes/cases/ieee14/ieee14.json
andes/cases/ieee14/ieee14.raw
andes/cases/ieee14/ieee14_ac8b.xlsx
andes/cases/ieee14/ieee14_ace.xlsx
andes/cases/ieee14/ieee14_alter.xlsx
andes/cases/ieee14/ieee14_conn.xlsx
andes/cases/ieee14/ieee14_dgprct1.xlsx
andes/cases/ieee14/ieee14_dgprctext.xlsx
andes/cases/ieee14/ieee14_dyn_only.xlsx
andes/cases/ieee14/ieee14_esac1a.xlsx
andes/cases/ieee14/ieee14_esd1.xlsx
andes/cases/ieee14/ieee14_esd1u.xlsx
andes/cases/ieee14/ieee14_esdc1a.xlsx
andes/cases/ieee14/ieee14_esst1a.xlsx
andes/cases/ieee14/ieee14_esst3a.xlsx
andes/cases/ieee14/ieee14_esst4b.xlsx
andes/cases/ieee14/ieee14_exac1.json
andes/cases/ieee14/ieee14_exac1.xlsx
andes/cases/ieee14/ieee14_exac4.xlsx
andes/cases/ieee14/ieee14_fault.json
andes/cases/ieee14/ieee14_fault.xlsx
andes/cases/ieee14/ieee14_fload.json
andes/cases/ieee14/ieee14_full.xlsx
andes/cases/ieee14/ieee14_gast.xlsx
andes/cases/ieee14/ieee14_gentrip.xlsx
andes/cases/ieee14/ieee14_hygov.xlsx
andes/cases/ieee14/ieee14_hygov4.xlsx
andes/cases/ieee14/ieee14_hygovdb.xlsx
andes/cases/ieee14/ieee14_ieeet1.xlsx
andes/cases/ieee14/ieee14_ieeet3.xlsx
andes/cases/ieee14/ieee14_ieeevc.dyr
andes/cases/ieee14/ieee14_ieeevc.raw
andes/cases/ieee14/ieee14_ieeevc2.xlsx
andes/cases/ieee14/ieee14_ieesgo.xlsx
andes/cases/ieee14/ieee14_island.xlsx
andes/cases/ieee14/ieee14_jumper.xlsx
andes/cases/ieee14/ieee14_linetrip.xlsx
andes/cases/ieee14/ieee14_plbvfu1.xlsx
andes/cases/ieee14/ieee14_pll1.xlsx
andes/cases/ieee14/ieee14_pvd1.json
andes/cases/ieee14/ieee14_pvd1.xlsx
andes/cases/ieee14/ieee14_pvd1u.xlsx
andes-1.10.0.dist-info/licenses/LICENSE
andes-1.10.0.dist-info/METADATA
andes-1.10.0.dist-info/WHEEL
andes-1.10.0.dist-info/entry_points.txt
andes-1.10.0.dist-info/top_level.txt
andes-1.10.0.dist-info/RECORD
