Metadata-Version: 2.4
Name: andes
Version: 1.10.0
Summary: Python software for symbolic power system modeling and numerical analysis.
Author-email: Hantao Cui <cuihantao@gmail.com>
License: GPL-3.0-or-later
Project-URL: Homepage, https://github.com/curent/andes
Project-URL: Documentation, https://docs.andes.app/
Project-URL: Repository, https://github.com/curent/andes
Classifier: Development Status :: 4 - Beta
Classifier: Natural Language :: English
Classifier: Programming Language :: Python :: 3
Classifier: Programming Language :: Python :: 3.10
Classifier: Programming Language :: Python :: 3.11
Classifier: Programming Language :: Python :: 3.12
Classifier: License :: OSI Approved :: GNU General Public License v3 or later (GPLv3+)
Classifier: Environment :: Console
Requires-Python: >=3.10
License-File: LICENSE
Requires-Dist: kvxopt<1.4,>=1.3.2.0
Requires-Dist: numpy
Requires-Dist: scipy<=1.16.3
Requires-Dist: sympy!=1.10.0,>=1.6
Requires-Dist: pandas
Requires-Dist: matplotlib
Requires-Dist: openpyxl
Requires-Dist: xlsxwriter
Requires-Dist: dill
Requires-Dist: pathos
Requires-Dist: tqdm
Requires-Dist: ipywidgets
Requires-Dist: pyyaml
Requires-Dist: coloredlogs
Requires-Dist: chardet
Requires-Dist: psutil
Requires-Dist: texttable
Requires-Dist: numba
Provides-Extra: dev
Requires-Dist: coverage; extra == "dev"
Requires-Dist: pytest==7.4; extra == "dev"
Requires-Dist: pytest-xdist; extra == "dev"
Requires-Dist: nbmake; extra == "dev"
Requires-Dist: flake8; extra == "dev"
Requires-Dist: line_profiler; extra == "dev"
Requires-Dist: sphinx; extra == "dev"
Requires-Dist: ipython; extra == "dev"
Requires-Dist: numpydoc; extra == "dev"
Requires-Dist: sphinx-copybutton; extra == "dev"
Requires-Dist: sphinx-panels; extra == "dev"
Requires-Dist: sphinx-design; extra == "dev"
Requires-Dist: sphinx-selective-exclude; extra == "dev"
Requires-Dist: pydata-sphinx-theme; extra == "dev"
Requires-Dist: myst-parser>=0.15; extra == "dev"
Requires-Dist: myst-nb>=0.13; extra == "dev"
Requires-Dist: mdit-py-plugins<0.4,>=0.3.1; extra == "dev"
Requires-Dist: pre-commit; extra == "dev"
Provides-Extra: doc
Requires-Dist: sphinx; extra == "doc"
Requires-Dist: numpydoc; extra == "doc"
Requires-Dist: sphinx-copybutton; extra == "doc"
Requires-Dist: sphinx-panels; extra == "doc"
Requires-Dist: sphinx-design; extra == "doc"
Requires-Dist: sphinx-selective-exclude; extra == "doc"
Requires-Dist: pydata-sphinx-theme; extra == "doc"
Requires-Dist: myst-parser>=0.15; extra == "doc"
Requires-Dist: myst-nb>=0.13; extra == "doc"
Requires-Dist: mdit-py-plugins<0.4,>=0.3.1; extra == "doc"
Provides-Extra: interop
Requires-Dist: pandapower<=3.3,>=3; extra == "interop"
Requires-Dist: pypowsybl; extra == "interop"
Provides-Extra: web
Requires-Dist: ipywidgets==7.7; extra == "web"
Provides-Extra: all
Requires-Dist: andes[dev,doc,interop,web]; extra == "all"
Dynamic: license-file
